knw_kakaowork_api.py
knw_kakaowork_api/__init__.py
knw_kakaowork_api/api.py
knw_kakaowork_api/knw_kakaowork_api.py
knw_kakaowork_api-0.1.8.dist-info/METADATA
knw_kakaowork_api-0.1.8.dist-info/WHEEL
knw_kakaowork_api-0.1.8.dist-info/top_level.txt
knw_kakaowork_api-0.1.8.dist-info/RECORD
