Metadata-Version: 2.1
Name: knw-kakaowork-api
Version: 0.1.8
Home-page: https://github.com/daumsong/knw_kakaowork_api
Author: archon.oh
Author-email: archon.oh@knworks.co.kr
Keywords: knw,kakaowork,kakaoworkapi,work
Requires-Python: >=3.6
Requires-Dist: requests
